odoo/addons/project_timesheet_read_permission/__init__.py
odoo/addons/project_timesheet_read_permission/__manifest__.py
odoo/addons/project_timesheet_read_permission/models/__init__.py
odoo/addons/project_timesheet_read_permission/models/hr_timesheet.py
odoo12_addon_project_timesheet_read_permission-12.0.0.0.5.99.dev2.dist-info/METADATA
odoo12_addon_project_timesheet_read_permission-12.0.0.0.5.99.dev2.dist-info/WHEEL
odoo12_addon_project_timesheet_read_permission-12.0.0.0.5.99.dev2.dist-info/top_level.txt
odoo12_addon_project_timesheet_read_permission-12.0.0.0.5.99.dev2.dist-info/RECORD
